{
    "@context": "https://dev.omeka.org/omeka-s-sandbox/api-context",
    "@id": "https://dev.omeka.org/omeka-s-sandbox/api/resource_templates/5",
    "@type": "o:ResourceTemplate",
    "o:description_property": null,
    "o:id": 5,
    "o:label": "Television Series",
    "o:owner": {
        "@id": "https://dev.omeka.org/omeka-s-sandbox/api/users/2",
        "o:id": 2
    },
    "o:resource_class": {
        "@id": "https://dev.omeka.org/omeka-s-sandbox/api/resource_classes/34",
        "o:id": 34
    },
    "o:resource_template_property": [
        {
            "o:alternate_comment": null,
            "o:alternate_label": null,
            "o:data_type": [
                "literal"
            ],
            "o:is_private": false,
            "o:is_required": false,
            "o:property": {
                "@id": "https://dev.omeka.org/omeka-s-sandbox/api/properties/1",
                "o:id": 1
            }
        },
        {
            "o:alternate_comment": null,
            "o:alternate_label": null,
            "o:data_type": [],
            "o:is_private": false,
            "o:is_required": false,
            "o:property": {
                "@id": "https://dev.omeka.org/omeka-s-sandbox/api/properties/4",
                "o:id": 4
            }
        },
        {
            "o:alternate_comment": "Air date of pilot or first episode",
            "o:alternate_label": null,
            "o:data_type": [
                "literal"
            ],
            "o:is_private": false,
            "o:is_required": false,
            "o:property": {
                "@id": "https://dev.omeka.org/omeka-s-sandbox/api/properties/20",
                "o:id": 20
            }
        },
        {
            "o:alternate_comment": "(number of)",
            "o:alternate_label": "Seasons",
            "o:data_type": [
                "literal"
            ],
            "o:is_private": false,
            "o:is_required": false,
            "o:property": {
                "@id": "https://dev.omeka.org/omeka-s-sandbox/api/properties/25",
                "o:id": 25
            }
        },
        {
            "o:alternate_comment": null,
            "o:alternate_label": null,
            "o:data_type": [],
            "o:is_private": false,
            "o:is_required": false,
            "o:property": {
                "@id": "https://dev.omeka.org/omeka-s-sandbox/api/properties/2",
                "o:id": 2
            }
        },
        {
            "o:alternate_comment": null,
            "o:alternate_label": "Production Co.",
            "o:data_type": [],
            "o:is_private": false,
            "o:is_required": false,
            "o:property": {
                "@id": "https://dev.omeka.org/omeka-s-sandbox/api/properties/5",
                "o:id": 5
            }
        },
        {
            "o:alternate_comment": null,
            "o:alternate_label": "Cast",
            "o:data_type": [],
            "o:is_private": false,
            "o:is_required": false,
            "o:property": {
                "@id": "https://dev.omeka.org/omeka-s-sandbox/api/properties/34",
                "o:id": 34
            }
        },
        {
            "o:alternate_comment": null,
            "o:alternate_label": "Currently airing?",
            "o:data_type": [
                "customvocab:2"
            ],
            "o:is_private": false,
            "o:is_required": false,
            "o:property": {
                "@id": "https://dev.omeka.org/omeka-s-sandbox/api/properties/184",
                "o:id": 184
            }
        }
    ],
    "o:title_property": null
}