{
    "@context": "https://dev.omeka.org/omeka-s-sandbox/api-context",
    "@id": "https://dev.omeka.org/omeka-s-sandbox/api/items/2307",
    "@type": "o:Item",
    "dcterms:bibliographicCitation": [
        {
            "@value": "The Martha Washington Collection, Mount Vernon.",
            "is_public": true,
            "property_id": 48,
            "property_label": "Bibliographic Citation",
            "type": "literal"
        }
    ],
    "dcterms:creator": [
        {
            "@value": "John Parke Custis",
            "is_public": true,
            "property_id": 2,
            "property_label": "Creator",
            "type": "literal"
        }
    ],
    "dcterms:date": [
        {
            "@value": "1781-10-12",
            "is_public": true,
            "property_id": 7,
            "property_label": "Date",
            "type": "literal"
        }
    ],
    "dcterms:description": [
        {
            "@value": "This letter was written by John Parke (Jacky) Custis to his mother Martha Washington from the camp of the Continental Army in front of Yorktown. Very late in the war, Jacky joined the army as a civilian aide to General Washington. In the postscript, Jacky mentions his efforts to locate escaped slaves who had run away from Mount Vernon. He also depicts the terrible mortality that had taken place among the large numbers of African-Americans present at the siege, presumably in large part a result of smallpox.",
            "is_public": true,
            "property_id": 4,
            "property_label": "Description",
            "type": "literal"
        }
    ],
    "dcterms:language": [
        {
            "@value": "eng",
            "is_public": true,
            "property_id": 12,
            "property_label": "Language",
            "type": "literal"
        }
    ],
    "dcterms:rightsHolder": [
        {
            "@value": "Mount Vernon",
            "is_public": true,
            "property_id": 50,
            "property_label": "Rights Holder",
            "type": "literal"
        }
    ],
    "dcterms:subject": [
        {
            "@value": "Custis family news, escaped slaves",
            "is_public": true,
            "property_id": 3,
            "property_label": "Subject",
            "type": "literal"
        }
    ],
    "dcterms:title": [
        {
            "@value": "Letter, John Parke Custis to Martha Washington, October 12, 1781",
            "is_public": true,
            "property_id": 1,
            "property_label": "Title",
            "type": "literal"
        }
    ],
    "o:created": {
        "@type": "http://www.w3.org/2001/XMLSchema#dateTime",
        "@value": "2017-05-30T17:48:28+00:00"
    },
    "o:id": 2307,
    "o:is_public": true,
    "o:item_set": [
        {
            "@id": "https://dev.omeka.org/omeka-s-sandbox/api/item_sets/1910",
            "o:id": 1910
        }
    ],
    "o:media": [],
    "o:modified": {
        "@type": "http://www.w3.org/2001/XMLSchema#dateTime",
        "@value": "2017-05-30T17:50:18+00:00"
    },
    "o:owner": {
        "@id": "https://dev.omeka.org/omeka-s-sandbox/api/users/8",
        "o:id": 8
    },
    "o:resource_class": null,
    "o:resource_template": {
        "@id": "https://dev.omeka.org/omeka-s-sandbox/api/resource_templates/4",
        "o:id": 4
    },
    "o:site": [
        {
            "@id": "https://dev.omeka.org/omeka-s-sandbox/api/sites/2",
            "o:id": 2
        }
    ],
    "o:thumbnail": null,
    "o:title": "Letter, John Parke Custis to Martha Washington, October 12, 1781",
    "thumbnail_display_urls": {
        "large": null,
        "medium": null,
        "square": null
    }
}