{
    "@context": "https://dev.omeka.org/omeka-s-sandbox/api-context",
    "@id": "https://dev.omeka.org/omeka-s-sandbox/api/items/920",
    "@type": "o:Item",
    "dcterms:coverage": [
        {
            "@value": "2000-present",
            "is_public": true,
            "property_id": 14,
            "property_label": "Coverage",
            "type": "literal"
        }
    ],
    "dcterms:creator": [
        {
            "@value": "National Park Service",
            "is_public": true,
            "property_id": 2,
            "property_label": "Creator",
            "type": "literal"
        }
    ],
    "dcterms:date": [
        {
            "@value": "2013",
            "is_public": true,
            "property_id": 7,
            "property_label": "Date",
            "type": "literal"
        }
    ],
    "dcterms:description": [
        {
            "@value": "Washington, DC, is home to a number of softball leagues, most of which make use of the fields on the Mall. All of the fields are managed by the National Park Service and some are first come, first served. The six fields on the Washington Monument grounds, shown on this map, are assigned to individual softball teams by a yearly lottery.",
            "is_public": true,
            "property_id": 4,
            "property_label": "Description",
            "type": "literal"
        }
    ],
    "dcterms:format": [
        {
            "@value": "pdf",
            "is_public": true,
            "property_id": 9,
            "property_label": "Format",
            "type": "literal"
        }
    ],
    "dcterms:source": [
        {
            "@value": "National Park Service. View original.",
            "is_public": true,
            "property_id": 11,
            "property_label": "Source",
            "type": "literal"
        }
    ],
    "dcterms:title": [
        {
            "@value": "Washington Monument Softball Field Map",
            "is_public": true,
            "property_id": 1,
            "property_label": "Title",
            "type": "literal"
        }
    ],
    "o-module-mapping:marker": [
        {
            "@id": "https://dev.omeka.org/omeka-s-sandbox/api/mapping_markers/774",
            "o:id": 774
        }
    ],
    "o:created": {
        "@type": "http://www.w3.org/2001/XMLSchema#dateTime",
        "@value": "2017-04-25T18:38:41+00:00"
    },
    "o:id": 920,
    "o:is_public": true,
    "o:item_set": [
        {
            "@id": "https://dev.omeka.org/omeka-s-sandbox/api/item_sets/275",
            "o:id": 275
        }
    ],
    "o:media": [
        {
            "@id": "https://dev.omeka.org/omeka-s-sandbox/api/media/3267",
            "o:id": 3267
        }
    ],
    "o:modified": {
        "@type": "http://www.w3.org/2001/XMLSchema#dateTime",
        "@value": "2017-06-05T20:06:05+00:00"
    },
    "o:owner": {
        "@id": "https://dev.omeka.org/omeka-s-sandbox/api/users/1",
        "o:id": 1
    },
    "o:resource_class": null,
    "o:resource_template": null,
    "o:site": [
        {
            "@id": "https://dev.omeka.org/omeka-s-sandbox/api/sites/4",
            "o:id": 4
        }
    ],
    "o:thumbnail": null,
    "o:title": "Washington Monument Softball Field Map",
    "thumbnail_display_urls": {
        "large": "https://dev.omeka.org/omeka-s-sandbox/files/large/dc1b9bca35317654f560e5aa56b1b98c8c7607f2.jpg",
        "medium": "https://dev.omeka.org/omeka-s-sandbox/files/medium/dc1b9bca35317654f560e5aa56b1b98c8c7607f2.jpg",
        "square": "https://dev.omeka.org/omeka-s-sandbox/files/square/dc1b9bca35317654f560e5aa56b1b98c8c7607f2.jpg"
    }
}